raspy_qmc5883l
