Metadata-Version: 2.1
Name: raspy-qmc5883l
Version: 0.2.9
Summary: Python driver for the QMC5883L 3-axis magnetic sensor
Home-page: https://github.com/RigacciOrg/py-qmc5883l
Author: Yanfu Zhou
Author-email: yanfu.zhou@outlook.com
License: UNKNOWN
Platform: UNKNOWN
Classifier: Programming Language :: Python
Classifier: License :: OSI Approved :: GNU Lesser General Public License v3 or later (LGPLv3+)
Classifier: Operating System :: OS Independent
License-File: LICENSE
